docs/conf.py
docs/_build/dirhtml/_static/__init__.py
miplearn/__init__.py
miplearn/h5.py
miplearn/io.py
miplearn/parallel.py
miplearn/classifiers/__init__.py
miplearn/classifiers/minprob.py
miplearn/classifiers/singleclass.py
miplearn/collectors/__init__.py
miplearn/collectors/basic.py
miplearn/collectors/priority.py
miplearn/components/__init__.py
miplearn/components/priority.py
miplearn/components/cuts/__init__.py
miplearn/components/cuts/expert.py
miplearn/components/cuts/mem.py
miplearn/components/lazy/__init__.py
miplearn/components/lazy/expert.py
miplearn/components/lazy/mem.py
miplearn/components/primal/__init__.py
miplearn/components/primal/actions.py
miplearn/components/primal/expert.py
miplearn/components/primal/indep.py
miplearn/components/primal/joint.py
miplearn/components/primal/mem.py
miplearn/extractors/AlvLouWeh2017.py
miplearn/extractors/__init__.py
miplearn/extractors/abstract.py
miplearn/extractors/dummy.py
miplearn/extractors/fields.py
miplearn/problems/__init__.py
miplearn/problems/binpack.py
miplearn/problems/multiknapsack.py
miplearn/problems/pmedian.py
miplearn/problems/setcover.py
miplearn/problems/setpack.py
miplearn/problems/stab.py
miplearn/problems/tsp.py
miplearn/problems/uc.py
miplearn/problems/vertexcover.py
miplearn/solvers/__init__.py
miplearn/solvers/abstract.py
miplearn/solvers/gurobi.py
miplearn/solvers/learning.py
miplearn/solvers/pyomo.py
tests/__init__.py
tests/conftest.py
tests/test_h5.py
tests/test_lazy_pyomo.py
tests/test_solvers.py
tests/components/__init__.py
tests/components/cuts/__init__.py
tests/components/cuts/test_mem.py
tests/components/lazy/__init__.py
tests/components/lazy/test_mem.py
tests/components/primal/__init__.py
tests/components/primal/test_expert.py
tests/components/primal/test_indep.py
tests/components/primal/test_joint.py
tests/components/primal/test_mem.py
tests/extractors/__init__.py
tests/extractors/test_dummy.py
tests/extractors/test_fields.py
tests/fixtures/gen_stab.py
tests/fixtures/gen_tsp.py
miplearn-0.4.3.dist-info/LICENSE
miplearn-0.4.3.dist-info/METADATA
miplearn-0.4.3.dist-info/WHEEL
miplearn-0.4.3.dist-info/top_level.txt
miplearn-0.4.3.dist-info/RECORD
