Metadata-Version: 2.1
Name: miplearn
Version: 0.4.3
Summary: Extensible Framework for Learning-Enhanced Mixed-Integer Optimization
Home-page: https://github.com/ANL-CEEESA/MIPLearn/
Author: Alinson S. Xavier
Author-email: axavier@anl.gov
Requires-Python: >=3.9
License-File: LICENSE
Requires-Dist: Jinja2 <3.1
Requires-Dist: gurobipy <13,>=12
Requires-Dist: h5py <4,>=3
Requires-Dist: networkx <3,>=2
Requires-Dist: numpy <2,>=1
Requires-Dist: pandas <2,>=1
Requires-Dist: pathos <0.3,>=0.2
Requires-Dist: pyomo <7,>=6
Requires-Dist: scikit-learn <2,>=1
Requires-Dist: scipy <2,>=1
Requires-Dist: tqdm <5,>=4
Provides-Extra: dev
Requires-Dist: Sphinx <4,>=3 ; extra == 'dev'
Requires-Dist: black ==22.6.0 ; extra == 'dev'
Requires-Dist: mypy ==1.8 ; extra == 'dev'
Requires-Dist: myst-parser ==0.14.0 ; extra == 'dev'
Requires-Dist: nbsphinx <0.10,>=0.9 ; extra == 'dev'
Requires-Dist: pyflakes ==2.5.0 ; extra == 'dev'
Requires-Dist: pytest <8,>=7 ; extra == 'dev'
Requires-Dist: sphinx-book-theme ==0.1.0 ; extra == 'dev'
Requires-Dist: sphinxcontrib-applehelp ==1.0.4 ; extra == 'dev'
Requires-Dist: sphinxcontrib-devhelp ==1.0.2 ; extra == 'dev'
Requires-Dist: sphinxcontrib-htmlhelp ==2.0.1 ; extra == 'dev'
Requires-Dist: sphinxcontrib-serializinghtml ==1.1.5 ; extra == 'dev'
Requires-Dist: sphinxcontrib-qthelp ==1.0.3 ; extra == 'dev'
Requires-Dist: sphinx-multitoc-numbering <0.2,>=0.1 ; extra == 'dev'
Requires-Dist: twine <7,>=6 ; extra == 'dev'
